anf_generator/CoherenceMatrix.py
anf_generator/MixingMatrix.py
anf_generator/__init__.py
anf_generator-0.1.2.dist-info/LICENSE
anf_generator-0.1.2.dist-info/METADATA
anf_generator-0.1.2.dist-info/WHEEL
anf_generator-0.1.2.dist-info/top_level.txt
anf_generator-0.1.2.dist-info/RECORD
