Metadata-Version: 2.1
Name: anf-generator
Version: 0.1.2
Summary: Generating coherence-constrained multisensor signals.
Author-email: Emanuel Habets <emanuel.habets@audiolabs-erlangen.de>
License: MIT License
Project-URL: Homepage, https://github.com/audiolabs/anf-generator
Project-URL: Issues, https://github.com/audiolabs/anf-generator/issues
Classifier: Programming Language :: Python :: 3
Classifier: License :: OSI Approved :: MIT License
Classifier: Operating System :: OS Independent
Requires-Python: >=3.8
License-File: LICENSE
Requires-Dist: numpy >=1.6
Requires-Dist: scipy >=0.13.0
